plasma_fhir_client_py/FHIRClient.py
plasma_fhir_client_py/PlasmaFHIRClient.py
plasma_fhir_client_py/PlasmaPlatformClient.py
plasma_fhir_client_py/RESTClient.py
plasma_fhir_client_py/__init__.py
plasma_fhir_client_py/example.py
tests/__init__.py
tests/test_FHIRClient.py
tests/test_PlasmaPlatformClient.py
tests/test_RESTClient.py
tests/test_example.py
plasma_fhir_client_py-0.0.12.dist-info/LICENSE
plasma_fhir_client_py-0.0.12.dist-info/METADATA
plasma_fhir_client_py-0.0.12.dist-info/WHEEL
plasma_fhir_client_py-0.0.12.dist-info/top_level.txt
plasma_fhir_client_py-0.0.12.dist-info/RECORD
