Metadata-Version: 2.1
Name: plasma-fhir-client-py
Version: 0.0.12
Summary: Plasma FHIR Client for Python
Home-page: https://plasmahealth.net
Author: Eric Morgan
Author-email: plasmafhir@gmail.com
License: MIT
Platform: UNKNOWN
Classifier: Programming Language :: Python :: 3
Classifier: License :: OSI Approved :: MIT License
Classifier: Operating System :: OS Independent
License-File: LICENSE
